README.md
setup.py
precise_runner/__init__.py
precise_runner/runner.py
precise_runner.egg-info/PKG-INFO
precise_runner.egg-info/SOURCES.txt
precise_runner.egg-info/dependency_links.txt
precise_runner.egg-info/requires.txt
precise_runner.egg-info/top_level.txt
precise_runner.egg-info/zip-safe