Metadata-Version: 1.1
Name: precise-runner
Version: 0.1.0
Summary: Wrapper to use Mycroft Precise Wake Word Listener
Home-page: http://github.com/MycroftAI/mycroft-precise
Author: Matthew Scholefield
Author-email: matthew.scholefield@mycroft.ai
License: UNKNOWN
Keywords: wakeword keyword wake word listener sound
Platform: UNKNOWN
Classifier: Development Status :: 3 - Alpha
Classifier: Intended Audience :: Developers
Classifier: Topic :: Text Processing :: Linguistic
Classifier: Programming Language :: Python :: 2
Classifier: Programming Language :: Python :: 2.7
Classifier: Programming Language :: Python :: 3
Classifier: Programming Language :: Python :: 3.0
Classifier: Programming Language :: Python :: 3.1
Classifier: Programming Language :: Python :: 3.2
Classifier: Programming Language :: Python :: 3.3
Classifier: Programming Language :: Python :: 3.4
Classifier: Programming Language :: Python :: 3.5
Classifier: Programming Language :: Python :: 3.6
